{
  "$type": "Happening",
  "Quest": "Голодные Бандиты 1",
  "Title": "Голодные_Бандиты_Послествие",
  "Nodes": [
    {
      "$type": "Node",
      "Step": 1,
      "Phrases": [
        {
          "$type": "Phrase",
          "Index": 0,
          "Text": "Разбойники, злобно оскалившись, бросаются прямо на вас. В их руках дубинки, ножи и топоры. Но мужчины из вашего отряда решительно дают им отпор. После короткой и жесткой стычки, большая часть бандитов в панике рассеиваются. Не обошлось и без убитых. А, кроме того, несколько противников оказались в вашем плену."
        },
        {
          "$type": "Phrase",
          "Index": 1,
          "Text": "К вам подводят пленных бандитов. Они сильно побитые, разорванная одежда висит клочьями. Часть ваших спутников смотрит на них с сожалением. Но другие явно желают расправы."
        }
      ],
      "Answers": [
        {
          "$type": "Answer",
          "Text": "Приказать убить пленников.",
          "ToStep": 0,
          "IsRestriction": false,
          "Index": 0,
          "Restriction": {
            "$type": "Restriction",
            "PersonName": {
              "$type": "PersonName",
              "Name": ""
            },
            "Value": 0
          },
          "IsConsequences": true,
          "Consequences": {
            "$type": "Consequences",
            "ParamConsequences": [
              {
                "$type": "SingleParamConsequences",
                "ParameterType": 3,
                "Value": -3
              },
              {
                "$type": "SingleParamConsequences",
                "ParameterType": 1,
                "Value": 10
              },
              {
                "$type": "SingleParamConsequences",
                "ParameterType": 2,
                "Value": -5
              }
            ],
            "QuestConsequences": [
              {
                "$type": "SingleQuestConsequences",
                "Quest": "Голодные Бандиты 1",
                "Happening": "Голодные_Бандиты3_Случай"
              }
            ],
            "PersonConsequences": [
              {
                "$type": "SinglePersonConsequences",
                "PersonName": {
                  "$type": "PersonName",
                  "Name": "Егише"
                },
                "Value": 1
              },
              {
                "$type": "SinglePersonConsequences",
                "PersonName": {
                  "$type": "PersonName",
                  "Name": "Господин Ваан"
                },
                "Value": -1
              },
              {
                "$type": "SinglePersonConsequences",
                "PersonName": {
                  "$type": "PersonName",
                  "Name": "Гарегин Востанци"
                },
                "Value": 1
              },
              {
                "$type": "SinglePersonConsequences",
                "PersonName": {
                  "$type": "PersonName",
                  "Name": "Барсег"
                },
                "Value": -1
              },
              {
                "$type": "SinglePersonConsequences",
                "PersonName": {
                  "$type": "PersonName",
                  "Name": "Тер-Григор"
                },
                "Value": -1
              },
              {
                "$type": "SinglePersonConsequences",
                "PersonName": {
                  "$type": "PersonName",
                  "Name": "Мариам"
                },
                "Value": -1
              }
            ],
            "HappenConsequences": [],
            "IsParamCons": true,
            "IsQuestCons": true,
            "IsPersonCons": true,
            "IsHappenCons": false,
            "IsMessage": false
          },
          "AfterAction": {
            "$type": "AfterAction",
            "Immediately": false,
            "Quest": "Голодные Бандиты 1",
            "SetupCamp": false,
            "DialogAvailable": 1,
            "LeaveCamp": false,
            "IsAfterAction": false,
            "IsActivateQuest": true
          }
        },
        {
          "$type": "Answer",
          "Text": "Проявить милосердие и позволить пленникам уйти.",
          "ToStep": 0,
          "IsRestriction": false,
          "Index": 1,
          "Restriction": {
            "$type": "Restriction",
            "PersonName": {
              "$type": "PersonName",
              "Name": ""
            },
            "Value": 0
          },
          "IsConsequences": true,
          "Consequences": {
            "$type": "Consequences",
            "ParamConsequences": [
              {
                "$type": "SingleParamConsequences",
                "ParameterType": 3,
                "Value": -3
              },
              {
                "$type": "SingleParamConsequences",
                "ParameterType": 1,
                "Value": 10
              },
              {
                "$type": "SingleParamConsequences",
                "ParameterType": 2,
                "Value": -5
              }
            ],
            "QuestConsequences": [
              {
                "$type": "SingleQuestConsequences",
                "Quest": "Голодные Бандиты 1",
                "Happening": "Голодные_Бандиты4_Случай"
              }
            ],
            "PersonConsequences": [
              {
                "$type": "SinglePersonConsequences",
                "PersonName": {
                  "$type": "PersonName",
                  "Name": "Егише"
                },
                "Value": -1
              },
              {
                "$type": "SinglePersonConsequences",
                "PersonName": {
                  "$type": "PersonName",
                  "Name": "Госпожа Рузан"
                },
                "Value": 1
              },
              {
                "$type": "SinglePersonConsequences",
                "PersonName": {
                  "$type": "PersonName",
                  "Name": "Гарегин Востанци"
                },
                "Value": -1
              },
              {
                "$type": "SinglePersonConsequences",
                "PersonName": {
                  "$type": "PersonName",
                  "Name": "Тер-Григор"
                },
                "Value": 1
              },
              {
                "$type": "SinglePersonConsequences",
                "PersonName": {
                  "$type": "PersonName",
                  "Name": "Мариам"
                },
                "Value": 1
              }
            ],
            "HappenConsequences": [],
            "IsParamCons": true,
            "IsQuestCons": true,
            "IsPersonCons": true,
            "IsHappenCons": false,
            "IsMessage": false
          },
          "AfterAction": {
            "$type": "AfterAction",
            "Immediately": false,
            "Quest": "Голодные Бандиты 1",
            "SetupCamp": false,
            "DialogAvailable": 1,
            "LeaveCamp": false,
            "IsAfterAction": false,
            "IsActivateQuest": false
          }
        },
        {
          "$type": "Answer",
          "Text": "Позволить пленникам присоединиться к отряду.",
          "ToStep": 0,
          "IsRestriction": false,
          "Index": 2,
          "Restriction": {
            "$type": "Restriction",
            "PersonName": {
              "$type": "PersonName",
              "Name": ""
            },
            "Value": 0
          },
          "IsConsequences": true,
          "Consequences": {
            "$type": "Consequences",
            "ParamConsequences": [
              {
                "$type": "SingleParamConsequences",
                "ParameterType": 3,
                "Value": 4
              },
              {
                "$type": "SingleParamConsequences",
                "ParameterType": 3,
                "Value": -3
              },
              {
                "$type": "SingleParamConsequences",
                "ParameterType": 1,
                "Value": 10
              },
              {
                "$type": "SingleParamConsequences",
                "ParameterType": 2,
                "Value": -5
              }
            ],
            "QuestConsequences": [
              {
                "$type": "SingleQuestConsequences",
                "Quest": "Голодные Бандиты 1",
                "Happening": "Голодные_Бандиты2_случай"
              }
            ],
            "PersonConsequences": [
              {
                "$type": "SinglePersonConsequences",
                "PersonName": {
                  "$type": "PersonName",
                  "Name": "Егише"
                },
                "Value": -1
              },
              {
                "$type": "SinglePersonConsequences",
                "PersonName": {
                  "$type": "PersonName",
                  "Name": "Госпожа Рузан"
                },
                "Value": 1
              },
              {
                "$type": "SinglePersonConsequences",
                "PersonName": {
                  "$type": "PersonName",
                  "Name": "Гарегин Востанци"
                },
                "Value": -1
              },
              {
                "$type": "SinglePersonConsequences",
                "PersonName": {
                  "$type": "PersonName",
                  "Name": "Василий"
                },
                "Value": -1
              },
              {
                "$type": "SinglePersonConsequences",
                "PersonName": {
                  "$type": "PersonName",
                  "Name": "Тер-Григор"
                },
                "Value": 1
              },
              {
                "$type": "SinglePersonConsequences",
                "PersonName": {
                  "$type": "PersonName",
                  "Name": "Мариам"
                },
                "Value": -1
              }
            ],
            "HappenConsequences": [
              {
                "$type": "SingleHappeningConsequences",
                "Quest": "Голодные Бандиты 1",
                "OldHappening": "Голодные_Бандиты2_случай",
                "NewHappening": "-----"
              }
            ],
            "IsParamCons": true,
            "IsQuestCons": true,
            "IsPersonCons": true,
            "IsHappenCons": false,
            "IsMessage": false
          },
          "AfterAction": {
            "$type": "AfterAction",
            "Immediately": false,
            "Quest": "Голодные Бандиты 1",
            "SetupCamp": false,
            "DialogAvailable": 1,
            "LeaveCamp": false,
            "IsAfterAction": false,
            "IsActivateQuest": false
          }
        }
      ],
      "Advices": [],
      "IsFocus": false,
      "IsShowFace": false
    }
  ],
  "Priority": 0,
  "IsBegin": false
}
