{
  "$type": "Happening",
  "Quest": "Прощание с павшими",
  "Title": "Прощание с павшими_1",
  "Nodes": [
    {
      "$type": "Node",
      "Step": 1,
      "Phrases": [
        {
          "$type": "Phrase",
          "Index": 0,
          "Text": "На одном из коротких привалов к вам подходит Тер-Григор. Священник выглядит немного сконфуженным, но, при этом возбужденным. Он едва сдерживает нетерпение, прежде чем начать разговор."
        }
      ],
      "Answers": [
        {
          "$type": "Answer",
          "ToStep": 0,
          "IsRestriction": false,
          "Index": 0,
          "Restriction": {
            "$type": "Restriction",
            "PersonName": {
              "$type": "PersonName",
              "Name": ""
            },
            "Value": 0
          },
          "IsConsequences": true,
          "Consequences": {
            "$type": "Consequences",
            "ParamConsequences": [],
            "QuestConsequences": [
              {
                "$type": "SingleQuestConsequences",
                "Quest": "Прощание с павшими",
                "Happening": "Прощание с павшими_2"
              }
            ],
            "PersonConsequences": [],
            "HappenConsequences": [],
            "IsParamCons": false,
            "IsQuestCons": true,
            "IsPersonCons": false,
            "IsHappenCons": false,
            "IsMessage": false
          },
          "AfterAction": {
            "$type": "AfterAction",
            "Immediately": true,
            "Quest": "Прощание с павшими",
            "SetupCamp": false,
            "DialogAvailable": 1,
            "LeaveCamp": false,
            "IsAfterAction": true,
            "IsActivateQuest": true
          }
        }
      ],
      "Advices": [],
      "IsFocus": false,
      "IsShowFace": false
    }
  ],
  "Priority": 1,
  "IsBegin": true
}
