{
  "$type": "Happening",
  "Quest": "Событие решение Конфликтов2",
  "Title": "Решение_Конфликтов2_Случай1",
  "Nodes": [
    {
      "$type": "Node",
      "Step": 1,
      "Phrases": [
        {
          "$type": "Phrase",
          "Index": 0,
          "Text": "В последнее время среди ваших людей участились ссоры и споры. Народ, то не может поделить лишнюю лепешку хлеба, то спорит из-за места у костра… Все это сильно бьет по сплоченности, которая так нужна в эти непростые времена. Вы спрашиваете у своих спутников, кто мог бы помочь вам в разрешении этих конфликтов. С большой охотой вызывается Тер-Григор и, как ни странно, Егише."
        }
      ],
      "Answers": [
        {
          "$type": "Answer",
          "ToStep": 0,
          "IsRestriction": false,
          "Index": 0,
          "Restriction": {
            "$type": "Restriction",
            "PersonName": {
              "$type": "PersonName",
              "Name": ""
            },
            "Value": 0
          },
          "IsConsequences": true,
          "Consequences": {
            "$type": "Consequences",
            "ParamConsequences": [],
            "QuestConsequences": [
              {
                "$type": "SingleQuestConsequences",
                "Quest": "Событие решение Конфликтов2",
                "Happening": "Решение_Конфликтов2_Диалог"
              }
            ],
            "PersonConsequences": [],
            "HappenConsequences": [],
            "IsParamCons": false,
            "IsQuestCons": true,
            "IsPersonCons": false,
            "IsHappenCons": false,
            "IsMessage": false
          },
          "AfterAction": {
            "$type": "AfterAction",
            "Immediately": true,
            "Quest": "Событие решение Конфликтов2",
            "SetupCamp": false,
            "DialogAvailable": 1,
            "LeaveCamp": false,
            "IsAfterAction": true,
            "IsActivateQuest": true
          }
        }
      ],
      "Advices": [],
      "IsFocus": false,
      "IsShowFace": false
    }
  ],
  "Priority": 2,
  "IsBegin": true
}
