{
  "$type": "Happening",
  "Quest": "Событие Утешение",
  "Title": "Утешение_Случай1",
  "Nodes": [
    {
      "$type": "Node",
      "Step": 1,
      "Phrases": [
        {
          "$type": "Phrase",
          "Index": 0,
          "Text": "Среди ваших людей все чаще звучат слова отчаяния. Люди устали от тяжкой дороги, от пережитого горя и от постоянного страха. Некотрые совсем опустили руки и каждое утро их приходится едва ли не силой заставлять встать и продолжить двигаться дальше. Требуется кто-то, кто смог бы поднять их моральный дух. Тер-Григор рвется выполнить эту задачу. Но госпожа Рузан считает, что справится с этим не хуже."
        }
      ],
      "Answers": [
        {
          "$type": "Answer",
          "ToStep": 0,
          "IsRestriction": false,
          "Index": 0,
          "Restriction": {
            "$type": "Restriction",
            "PersonName": {
              "$type": "PersonName",
              "Name": ""
            },
            "Value": 0
          },
          "IsConsequences": true,
          "Consequences": {
            "$type": "Consequences",
            "ParamConsequences": [],
            "QuestConsequences": [
              {
                "$type": "SingleQuestConsequences",
                "Quest": "Событие Утешение",
                "Happening": "Утешение_Диалог"
              }
            ],
            "PersonConsequences": [],
            "HappenConsequences": [],
            "IsParamCons": false,
            "IsQuestCons": true,
            "IsPersonCons": false,
            "IsHappenCons": false,
            "IsMessage": false
          },
          "AfterAction": {
            "$type": "AfterAction",
            "Immediately": true,
            "SetupCamp": false,
            "DialogAvailable": 1,
            "LeaveCamp": false,
            "IsAfterAction": false,
            "IsActivateQuest": false
          }
        }
      ],
      "Advices": [],
      "IsFocus": false,
      "IsShowFace": false
    }
  ],
  "Priority": 2,
  "IsBegin": true
}
